kurama/__init__.py
kurama/__main__.py
kurama/meme.py
kurama-1.0.1.dist-info/LICENSE
kurama-1.0.1.dist-info/METADATA
kurama-1.0.1.dist-info/WHEEL
kurama-1.0.1.dist-info/entry_points.txt
kurama-1.0.1.dist-info/top_level.txt
kurama-1.0.1.dist-info/zip-safe
kurama-1.0.1.dist-info/RECORD
